csctracker_py_core/__init__.py
csctracker_py_core/starter.py
csctracker_py_core/models/__init__.py
csctracker_py_core/models/emuns/__init__.py
csctracker_py_core/models/emuns/config.py
csctracker_py_core/repository/__init__.py
csctracker_py_core/repository/http_repository.py
csctracker_py_core/repository/remote_repository.py
csctracker_py_core/utils/__init__.py
csctracker_py_core/utils/configs.py
csctracker_py_core/utils/interceptor.py
csctracker_py_core/utils/request_info.py
csctracker_py_core/utils/utils.py
csctracker_py_core/utils/version.py
csctracker_py_core-24.6.4.dist-info/LICENSE
csctracker_py_core-24.6.4.dist-info/METADATA
csctracker_py_core-24.6.4.dist-info/WHEEL
csctracker_py_core-24.6.4.dist-info/top_level.txt
csctracker_py_core-24.6.4.dist-info/RECORD
