Metadata-Version: 2.1
Name: csctracker-py-core
Version: 24.6.4
Summary: A library for handle scheduled jobs.
Home-page: https://github.com/krlsedu/CscTrackerPyCore.git
Author: Carlos Eduardo
License: MIT
Keywords: queue,scheduled,scheduler
Platform: UNKNOWN
Classifier: Intended Audience :: Developers
Classifier: Programming Language :: Python :: 3
Classifier: Programming Language :: Python :: 3.9
Classifier: Topic :: Software Development
Requires-Python: >=3
Requires-Dist: csctracker-queue-scheduler ==24.6.1
Requires-Dist: flask ~=3.0.0
Requires-Dist: python-json-logger
Requires-Dist: python-dotenv ~=1.0.0
Requires-Dist: requests ~=2.31.0
Requires-Dist: beautifulsoup4 ==4.10.0
Requires-Dist: flask-cors ~=3.0.7
Requires-Dist: prometheus-flask-exporter ==0.22.4
Requires-Dist: flask-swagger-init ==23.52.4
Requires-Dist: pytz ~=2023.3.post1
